bqplot_image_gl/__init__.py
bqplot_image_gl/_version.py
bqplot_image_gl/imagegl.py
bqplot_image_gl/interacts.py
bqplot_image_gl/linesgl.py
bqplot_image_gl/serialize.py
bqplot_image_gl/viewlistener.py
bqplot_image_gl/labextension/225.69db50aa9ce2441cb7d5.js
bqplot_image_gl/labextension/270.b874982a3db5a09ba8f3.js
bqplot_image_gl/labextension/355.0974b7e188350954ef71.js
bqplot_image_gl/labextension/493.f7c7992512ad4c5c8cc1.js
bqplot_image_gl/labextension/509.16332d7720d5f328c65f.js
bqplot_image_gl/labextension/543.afc5bee3549afb8d59f5.js
bqplot_image_gl/labextension/543.afc5bee3549afb8d59f5.js.LICENSE.txt
bqplot_image_gl/labextension/570.a56e41c6881bdb775466.js
bqplot_image_gl/labextension/570.a56e41c6881bdb775466.js.LICENSE.txt
bqplot_image_gl/labextension/716.74b0bda1dcfaefb5f222.js
bqplot_image_gl/labextension/964.48dc4eb56695802f3476.js
bqplot_image_gl/labextension/964.48dc4eb56695802f3476.js.LICENSE.txt
bqplot_image_gl/labextension/imports.css
bqplot_image_gl/labextension/package.json
bqplot_image_gl/labextension/remoteEntry.2390a95a15017029df92.js
bqplot_image_gl/nbextension/extension.js
bqplot_image_gl/nbextension/index.js
bqplot_image_gl/nbextension/index.js.LICENSE.txt
bqplot_image_gl/nbextension/index.js.map
bqplot_image_gl/tests/__init__.py
bqplot_image_gl/tests/test_imagegl.py
js/README.md
js/_pl_new.json
js/bqplot-image-gl-1.7.0.tgz
js/package-lock.json
js/package.json
js/webpack.config.js
js/lib/BrushEllipseSelector.js
js/lib/BrushEllipseSelectorModel.js
js/lib/BrushRectangleSelector.js
js/lib/BrushRectangleSelectorModel.js
js/lib/MouseInteraction.js
js/lib/ViewListener.js
js/lib/contour.js
js/lib/embed.js
js/lib/extension.js
js/lib/imagegl.js
js/lib/index.js
js/lib/labplugin.js
js/lib/linesgl.js
js/lib/serialize.js
js/lib/utils.js
js/lib/values.js
js/lib/version.js
js/lib/examples/lines/Line2.js
js/lib/examples/lines/LineGeometry.js
js/lib/examples/lines/LineMaterial.js
js/lib/examples/lines/LineSegments2.js
bqplot_image_gl-1.7.0.dist-info/METADATA
bqplot_image_gl-1.7.0.dist-info/WHEEL
bqplot_image_gl-1.7.0.dist-info/licenses/LICENSE
bqplot_image_gl-1.7.0.dist-info/RECORD
