Metadata-Version: 2.4
Name: bqplot-image-gl
Version: 1.7.0
Summary: An ipywidget image widget for astronomical purposes
Project-URL: Homepage, https://github.com/glue-viz/bqplot-image-gl
Author-email: "Maarten A. Breddels" <maartenbreddels@gmail.com>
License: MIT
License-File: LICENSE
Keywords: ipython,jupyter,widgets
Classifier: Development Status :: 4 - Beta
Classifier: Framework :: IPython
Classifier: Intended Audience :: Developers
Classifier: Intended Audience :: Science/Research
Classifier: Programming Language :: Python :: 3
Classifier: Programming Language :: Python :: 3.7
Classifier: Programming Language :: Python :: 3.8
Classifier: Programming Language :: Python :: 3.9
Classifier: Programming Language :: Python :: 3.10
Classifier: Programming Language :: Python :: 3.11
Classifier: Programming Language :: Python :: 3.12
Classifier: Programming Language :: Python :: 3.13
Classifier: Topic :: Multimedia :: Graphics
Requires-Python: >=3.7
Requires-Dist: bqplot>=0.12
Requires-Dist: ipywidgets>=7.0.0
Requires-Dist: pillow
Requires-Dist: typing-extensions
